{
    "results": [{
        "columns": ["user", "entity"],
        "data": [{
            "graph": {
                "nodes": [{
                    "id": "1",
                    "labels": ["APPLYER"],
                    "properties": {
                        "name": "张三"
                    }
                }, {
                    "id": "2",
                    "labels": ["Phone"],
                    "properties": {
                        "value": "555-555-5555"
                    }
                }, {
                    "id": "3",
                    "labels": ["Address"],
                    "properties": {
                        "详细地址": "静安区康定路1199号",
                        "province": "上海市",
                        "city": "上海市"
                    }
                }, {
                    "id": "4",
                    "labels": ["BirthDate"],
                    "properties": {
                        "value": "2021-7-14"
                    }
                }, {
                    "id": "5",
                    "labels": ["Password"],
                    "properties": {
                        "value": "123456"
                    }
                }, {
                    "id": "6",
                    "labels": ["Device"],
                    "properties": {
                        "value": "eisman"
                    }
                }, {
                    "id": "7",
                    "labels": ["SecurityChallengeAnswer"],
                    "properties": {
                        "value": "hCxh4LItmWefWg71JiYUaxxFrCRaqQIDEoEbeqHa"
                    }
                }, {
                    "id": "8",
                    "labels": ["Project"],
                    "properties": {
                        "name": "neo4jd3",
                        "title": "neo4jd3.js",
                        "description": "Neo4j graph visualization using D3.js.",
                        "url": "https://eisman.github.io/neo4jd3"
                    }
                }],
                "relationships": [{
                    "id": "1",
                    "type": "HAS_PHONE_NUMBER",
                    "startNode": "1",
                    "endNode": "2",
                    "properties": {
                        "from": 1473581532586
                    }
                }, {
                    "id": "2",
                    "type": "HAS_ADDRESS",
                    "startNode": "1",
                    "endNode": "3",
                    "properties": {
                        "from": 1473581532586
                    }
                }, {
                    "id": "3",
                    "type": "HAS_BIRTH_DATE",
                    "startNode": "1",
                    "endNode": "4",
                    "properties": {
                        "from": 1473581532586
                    }
                }, {
                    "id": "4",
                    "type": "HAS_PASSWORD",
                    "startNode": "1",
                    "endNode": "5",
                    "properties": {
                        "from": 1473581532586
                    }
                }, {
                    "id": "5",
                    "type": "USED_DEVICE",
                    "startNode": "1",
                    "endNode": "6",
                    "properties": {
                        "from": 1473581532586
                    }
                }, {
                    "id": "6",
                    "type": "HAS_SECURITY_ANSWER",
                    "startNode": "1",
                    "endNode": "7",
                    "properties": {
                        "from": 1473581532586
                    }
                }, {
                    "id": "7",
                    "type": "DEVELOPES",
                    "startNode": "1",
                    "endNode": "8",
                    "properties": {
                        "from": 1470002400000
                    }
                }]
            }
        }]
    }],
    "errors": []
}
